beautiful_prints.py
printNestedData.py
beautiful_prints-0.1.3.dist-info/LICENSE
beautiful_prints-0.1.3.dist-info/METADATA
beautiful_prints-0.1.3.dist-info/WHEEL
beautiful_prints-0.1.3.dist-info/top_level.txt
beautiful_prints-0.1.3.dist-info/RECORD
