Metadata-Version: 2.1
Name: beautiful-prints
Version: 0.1.3
Summary: An easy way to make beautiful prints of nested data in python
Home-page: https://github.com/FredVB1/print-nested-data-python.git
Author: Frederic vB
License: MIT
Platform: UNKNOWN
